LICENSE
MANIFEST.in
README.md
requirements.txt
setup.py
fabber/__init__.py
fabber/_version.py
fabber/api.py
fabber/api_cl.py
fabber/api_shlib.py
fabber/model_test.py
fabber/mvn.py
fabber/test/__init__.py
fabber/test/test_exception.py
fabber/test/test_mvn.py
pyfab.egg-info/PKG-INFO
pyfab.egg-info/SOURCES.txt
pyfab.egg-info/dependency_links.txt
pyfab.egg-info/requires.txt
pyfab.egg-info/top_level.txt