Metadata-Version: 2.1
Name: pyfab
Version: 0.3.1
Summary: Python interface to the Fabber toolkit for Bayesian model fitting
Home-page: https://fabber_core.readthedocs.io/
Author: Martin Craig
Author-email: martin.craig@eng.ox.ac.uk
License: License granted by University of Oxford for use by academics carrying out research and not for use by consumers or commercial businesses. See LICENSE file for more details
Platform: UNKNOWN
Classifier: Development Status :: 3 - Alpha
Classifier: Intended Audience :: Science/Research
Classifier: Programming Language :: Python :: 2.7
Classifier: Programming Language :: Python :: 3
Classifier: Topic :: Scientific/Engineering :: Bio-Informatics
Classifier: License :: Free for non-commercial use
